warepy/__init__.py
warepy/load_yaml_test.py
warepy/noconflict.py
warepy/singleton.py
warepy/__pycache__/__init__.cpython-310.pyc
warepy/__pycache__/load_yaml_test.cpython-310-pytest-7.1.2.pyc
warepy/__pycache__/noconflict.cpython-310.pyc
warepy/__pycache__/singleton.cpython-310.pyc
warepy-0.7.1.dist-info/METADATA
warepy-0.7.1.dist-info/WHEEL
warepy-0.7.1.dist-info/top_level.txt
warepy-0.7.1.dist-info/RECORD
