Metadata-Version: 2.1
Name: warepy
Version: 0.7.1
Summary: My toolkit for Python.
Home-page: https://github.com/ryzhovalex/warepy
Author: Alexander Ryzhov
Author-email: thed4rkof@gmail.com
License: MIT
Keywords: toolkit,python-core
Platform: UNKNOWN
Classifier: Development Status :: 2 - Pre-Alpha
Classifier: Intended Audience :: Developers
Classifier: Topic :: Software Development :: Build Tools
Classifier: License :: OSI Approved :: MIT License
Classifier: Programming Language :: Python :: 3.10
Requires-Dist: pytest
Requires-Dist: pyyaml
